rororo/__init__.py
rororo/aio.py
rororo/annotations.py
rororo/logger.py
rororo/openapi/__init__.py
rororo/openapi/annotations.py
rororo/openapi/constants.py
rororo/openapi/contexts.py
rororo/openapi/core_data.py
rororo/openapi/core_validators.py
rororo/openapi/data.py
rororo/openapi/exceptions.py
rororo/openapi/middlewares.py
rororo/openapi/openapi.py
rororo/openapi/py.typed
rororo/openapi/security.py
rororo/openapi/utils.py
rororo/openapi/validators.py
rororo/openapi/views.py
rororo/py.typed
rororo/settings.py
rororo/timedelta.py
rororo/utils.py
rororo-3.3.0.dist-info/LICENSE
rororo-3.3.0.dist-info/METADATA
rororo-3.3.0.dist-info/WHEEL
rororo-3.3.0.dist-info/RECORD
