Metadata-Version: 2.1
Name: rororo
Version: 3.3.0
Summary: aiohttp.web OpenAPI 3 schema first server applications.
Home-page: https://igordavydenko.com/projects/#rororo
License: BSD-3-Clause
Keywords: aiohttp,aiohttp.web,oas,openapi,openapi schema,openapi3,schema first
Author: Igor Davydenko
Author-email: iam@igordavydenko.com
Requires-Python: >=3.8,<4.0
Classifier: Development Status :: 5 - Production/Stable
Classifier: Environment :: Web Environment
Classifier: Framework :: AsyncIO
Classifier: Intended Audience :: Developers
Classifier: License :: OSI Approved :: BSD License
Classifier: Operating System :: OS Independent
Classifier: Programming Language :: Python :: 3
Classifier: Programming Language :: Python :: 3.8
Classifier: Programming Language :: Python :: 3.9
Classifier: Programming Language :: Python :: 3.10
Classifier: Programming Language :: Python :: 3.11
Classifier: Programming Language :: Python :: 3.12
Classifier: Topic :: Internet :: WWW/HTTP
Classifier: Topic :: Internet :: WWW/HTTP :: WSGI
Classifier: Topic :: Internet :: WWW/HTTP :: WSGI :: Application
Classifier: Topic :: Utilities
Classifier: Typing :: Typed
Requires-Dist: aiohttp (>=3.8.1,<4.0.0)
Requires-Dist: aiohttp-middlewares (>=1.2.0,<3)
Requires-Dist: attrs (>=19.2.0,<25)
Requires-Dist: email-validator (>=1.0.5,<3.0.0)
Requires-Dist: environ-config (>=23.2.0,<25)
Requires-Dist: isodate (>=0.6.0,<0.7.0)
Requires-Dist: jsonschema (<=4.17.3)
Requires-Dist: openapi-core (>=0.13.4,<0.13.7)
Requires-Dist: openapi-spec-validator (==0.4.0)
Requires-Dist: pyrsistent (>=0.16,<0.21)
Requires-Dist: pyyaml (>=5.1,<7.0)
Project-URL: Bug Tracker, https://github.com/playpauseandstop/rororo/issues
Project-URL: Documentation, https://rororo.readthedocs.io/
Project-URL: Repository, https://github.com/playpauseandstop/rororo
